LICENSE
README.md
setup.cfg
setup.py
lasertools_traceprocess/__init__.py
lasertools_traceprocess/process.py
lasertools_traceprocess.egg-info/PKG-INFO
lasertools_traceprocess.egg-info/SOURCES.txt
lasertools_traceprocess.egg-info/dependency_links.txt
lasertools_traceprocess.egg-info/requires.txt
lasertools_traceprocess.egg-info/top_level.txt
lasertools_traceprocess/utilities/__init__.py
lasertools_traceprocess/utilities/background.py
lasertools_traceprocess/utilities/interpolate.py
lasertools_traceprocess/utilities/maxima.py
lasertools_traceprocess/utilities/normalize.py
lasertools_traceprocess/utilities/smooth.py
lasertools_traceprocess/utilities/threshold.py